boaviztapi_sdk
