Metadata-Version: 2.4
Name: boaviztapi_sdk
Version: 2.0.1
Summary: BoaviztAPI SDK for Python applications.
Home-page: 
Author: Boavizta
Author-email: OpenAPI Generator Community <team@openapitools.org>
Project-URL: Repository, https://github.com/boavizta/boaviztapi
Keywords: OpenAPI,OpenAPI-Generator,BoaviztAPI SDK for Python applications.
Requires-Python: >=3.9
Requires-Dist: urllib3<3.0.0,>=2.1.0
Requires-Dist: python-dateutil>=2.8.2
Requires-Dist: pydantic>=2
Requires-Dist: typing-extensions>=4.7.1
Dynamic: author
